EE3403_Project/fixedPointSquareroot.v
`timescale 1ns / 1ps

module fixedPointSquareroot(
    input [22:0] Y,
    input clk,
    output wire [23:0] result
);
    // Input is 23-bit mantissa; the first bit of Y is assumed to be 1
    wire [23:0] Y_new = {1'b1, Y}; // Hidden Bit
    wire [5:0] Y_cap = Y[22:17];

    reg [8:0] R_LUT [0:63];
    reg [27:0] M_LUT [0:63];

    reg [8:0] R;
    reg [27:0] M;

    // Combinational signals
    wire [31:0] product = R * Y_new;
    wire [23:0] A_raw = product[31:8] - 24'h800000;
    wire [23:0] A = A_raw[23] ? (~A_raw + 1'b1) : A_raw; // Two's complement if negative

    wire [6:0] A2 = A[15:9];
    wire [6:0] A3 = A[8:2];
    wire [23:0] A2_square = (A2 * A2) >> 5;
    wire [23:0] A2_cube = (A2 * A2 * A2) >> 19;
    wire [23:0] A2_A3_prod = (A2 * A3) >> 12;

    wire [23:0] term1 = 24'h800000;
    wire [23:0] term2 = A_raw[23] ? (A >> 1) : ({2'b0, A[23:1]});
    wire [23:0] term3 = A2_square >> 3;
    wire [23:0] term4 = A2_A3_prod >> 2;
    wire [23:0] term5 = A2_cube >> 4;

    wire [23:0] B = A_raw[23]
        ? (term1 - term2 - term3 - term4 - term5)
        : (term1 + term2 - term3 - term4 + term5);

    wire [50:0] prod = M * B;

    always @(posedge clk) begin
        $readmemb("lutR.mem", R_LUT);
        $readmemb("lutM.mem", M_LUT);

        R <= R_LUT[Y_cap];
        M <= M_LUT[Y_cap];
    end
    assign result = prod[50:27];
endmodule

EE3403_Project/fixedPointSquareroot_tb.v
module fixedPointSquareroot_tb;
    reg [22:0] Y;
    reg clk;
    wire [23:0] result;

    fixedPointSquareroot uut (
        .Y(Y),
        .clk(clk),
        .result(result)
    );

    initial begin
        clk = 1;
        forever #5 clk = ~clk;
    end

    initial begin
        $dumpfile("fixedPointSquareroot.vcd");
        $dumpvars();
        
        $display("Time\tclk\tY\tResult");
        
        #10 Y = 23'h400000; // Example input (e.g., 1.5 in fixed point)
        #10 Y = 23'h600000; // Example input (e.g., 1.75 in fixed point)
        #10 Y = 23'h7FF000; // Maximum value for testing
        #10 Y = 23'h001000; // Minimum value
        #10 Y = 23'h000000; // Minimum value
        #10 Y = 23'h3FFFFF; // Mid-range value
        #10 Y = 23'h5AAAAA; // Another mid-range value
        #5;
        $finish;
    end
endmodule

EE3403_Project/fixedPointSquareroot.vcd
$date
	Thu Nov 21 23:47:41 2024
$end
$version
	Icarus Verilog
$end
$timescale
	1ps
$end
$scope module fixedPointSquareroot_tb $end
$var wire 24 ! result [23:0] $end
$var reg 23 " Y [22:0] $end
$var reg 1 # clk $end
$scope module uut $end
$var wire 23 $ Y [22:0] $end
$var wire 1 # clk $end
$var wire 24 % term1 [23:0] $end
$var wire 24 & term5 [23:0] $end
$var wire 24 ' term4 [23:0] $end
$var wire 24 ( term3 [23:0] $end
$var wire 24 ) term2 [23:0] $end
$var wire 24 * result [23:0] $end
$var wire 32 + product [31:0] $end
$var wire 51 , prod [50:0] $end
$var wire 24 - Y_new [23:0] $end
$var wire 6 . Y_cap [5:0] $end
$var wire 24 / B [23:0] $end
$var wire 24 0 A_raw [23:0] $end
$var wire 7 1 A3 [6:0] $end
$var wire 24 2 A2_square [23:0] $end
$var wire 24 3 A2_cube [23:0] $end
$var wire 24 4 A2_A3_prod [23:0] $end
$var wire 7 5 A2 [6:0] $end
$var wire 24 6 A [23:0] $end
$var reg 28 7 M [27:0] $end
$var reg 9 8 R [8:0] $end
$upscope $end
$upscope $end
$enddefinitions $end
$comment Show the parameter values. $end
$dumpall
$end
#0
$dumpvars
bx 8
bx 7
bx 6
bx 5
b0xxxxxxxxxxxx 4
b0xxxxx 3
b0xxxxxxxxxxxxxxxxxxx 2
bx 1
bx 0
bx /
bx .
b1xxxxxxxxxxxxxxxxxxxxxxx -
bx ,
bx +
bx *
b0xxxxxxxxxxxxxxxxxxxxxxx )
b0xxxxxxxxxxxxxxxx (
b0xxxxxxxxxx '
b0x &
b100000000000000000000000 %
bx $
1#
bx "
bx !
$end
#5000
0#
#10000
b100111001100010001110000 !
b100111001100010001110000 *
b100111001100010001110000101001101011011001000110000 ,
b11111111011111111110000 /
b10000 (
b0 &
b0 '
b100000000000000 )
b10000000 2
b0 3
b0 4
b1000000 5
b0 1
b1000000000000000 6
b111111111000000000000000 0
b1001110100010011000011011101 7
b1111111100000000000000000000000 +
b10101010 8
b100000 .
1#
b110000000000000000000000 -
b10000000000000000000000 "
b10000000000000000000000 $
#15000
0#
#20000
b1010100101111110011000100011 7
b10010010 8
b100 (
b10000000000000 )
b100000 2
b0 3
b101010010101001111111101 !
b101010010101001111111101 *
b100000 5
b101010010101001111111101010010111000000011101110100 ,
b11111111101111111111100 /
b100000000000000 6
b111111111100000000000000 0
b110000 .
1#
b1111111110000000000000000000000 +
b111000000000000000000000 -
b11000000000000000000000 "
b11000000000000000000000 $
#25000
0#
#30000
b1011010001010000111111000000 7
b10000001 8
b111011 (
b111101111111000 )
b111011000 2
b11 3
b11 4
b101101001111111101001100 !
b101101001111111101001100 *
b1111011 5
b1111100 1
b101101001111111101001100000100011011110000011000000 ,
b100000000111101110111101 /
b1111011111110000 6
b1111011111110000 0
b111111 .
1#
b10000000111101111111000000000000 +
b111111111111000000000000 -
b11111111111000000000000 "
b11111111111000000000000 $
#35000
0#
#40000
b1000000000000000000000000000 7
b100000000 8
b0 (
b100000000000 )
b10 2
b0 3
b0 4
b100000000000100000000000 !
b100000000000100000000000 *
b1000 5
b0 1
b100000000000100000000000000000000000000000000000000 ,
b100000000000100000000000 /
b1000000000000 6
b1000000000000 0
b0 .
1#
b10000000000100000000000000000000 +
b100000000001000000000000 -
b1000000000000 "
b1000000000000 $
#45000
0#
#50000
b100000000000000000000000 !
b100000000000000000000000 *
b100000000000000000000000000000000000000000000000000 ,
b100000000000000000000000 /
b0 )
b0 2
b0 5
b0 6
b0 0
1#
b10000000000000000000000000000000 +
b100000000000000000000000 -
b0 "
b0 $
#55000
0#
#60000
b1001110000101000100101011101 7
b10101100 8
b100111001100010001110000 !
b100111001100010001110000 *
b100111001100010001110000010100011000010100011000000 ,
b100000000111111111000000 /
b111111 (
b111111111111111 )
b111111000 2
b11 3
b11 4
b1111111 5
b1111111 1
b1111111111111111 6
b1111111111111111 0
b11111 .
1#
b10000000111111111111111101010100 +
b101111111111111111111111 -
b1111111111111111111111 "
b1111111111111111111111 $
#65000
0#
#70000
b0 3
b1010011100110111111011111001 7
b10010110 8
b101001110100110011010101 !
b101001110100110011010101 *
b101001110100110011010101001111111000001000100000111 ,
b100000000000111111111111 /
b0 (
b111111111111 )
b111 2
b0 4
b1111 5
b1111111 1
b1111111111111 6
b1111111111111 0
b101101 .
1#
b10000000000111111111111110011100 +
b110110101010101010101010 -
b10110101010101010101010 "
b10110101010101010101010 $
