EE3403_Project/fixedPointSquareroot.v
`timescale 1ns / 1ps

module fixedPointSquareroot(
    input [22:0] Y,
    input clk,
    output wire [23:0] result
);
    // Input is 23-bit mantissa; the first bit of Y is assumed to be 1
    wire [23:0] Y_new = {1'b1, Y}; // Hidden Bit
    wire [5:0] Y_cap = Y[22:17];

    reg [8:0] R_LUT [0:63];
    reg [27:0] M_LUT [0:63];

    reg [8:0] R;
    reg [27:0] M;

    // Combinational signals
    wire [31:0] product = R * Y_new;
    wire [23:0] A_raw = product[31:8] - 24'h800000;
    wire [23:0] A = A_raw[23] ? (~A_raw + 1'b1) : A_raw; // Two's complement if negative

    wire [6:0] A2 = A[15:9];
    wire [6:0] A3 = A[8:2];
    wire [23:0] A2_square = (A2 * A2) >> 5;
    wire [23:0] A2_cube = (A2 * A2 * A2) >> 19;
    wire [23:0] A2_A3_prod = (A2 * A3) >> 12;

    wire [23:0] term1 = 24'h800000;
    wire [23:0] term2 = A_raw[23] ? (A >> 1) : ({2'b0, A[23:1]});
    wire [23:0] term3 = A2_square >> 3;
    wire [23:0] term4 = A2_A3_prod >> 2;
    wire [23:0] term5 = A2_cube >> 4;

    wire [23:0] B = A_raw[23]
        ? (term1 - term2 - term3 - term4 - term5)
        : (term1 + term2 - term3 - term4 + term5);

    wire [50:0] prod = M * B;

    always @(posedge clk) begin
        $readmemb("lutR.mem", R_LUT);
        $readmemb("lutM.mem", M_LUT);

        R <= R_LUT[Y_cap];
        M <= M_LUT[Y_cap];
    end
    assign result = prod[50:27];
endmodule

EE3403_Project/SquareRoot.v
`timescale 1ns / 1ps

module SquareRoot(
    input [31:0] floating_point_in,
    input clk,
    output reg [31:0] result
);
    wire sign = floating_point_in[31];
    wire [7:0] exponent = floating_point_in[30:23];
    wire [22:0] mantissa = floating_point_in[22:0];

    wire is_nan = (exponent == 8'hFF) && (mantissa != 0);
    wire is_pos_inf = (sign == 1'b0) && (exponent == 8'hFF) && (mantissa == 0);
    wire is_neg_inf = (sign == 1'b1) && (exponent == 8'hFF) && (mantissa == 0);
    wire is_zero = (exponent == 8'h00) && (mantissa == 0);
    
    reg odd_flag = 1'b0;

    reg [7:0] sqrt_exponent;
    reg [23:0] sqrt_mantissa;
    reg [23:0] adjusted_mantissa;
    reg [46:0] product;
    
    wire [23:0] fixed_sqrt_result;
    fixedPointSquareroot sqrt_inst (
        .Y(adjusted_mantissa[22:0]),
        .clk(clk),
        .result(fixed_sqrt_result)
    );

    parameter ROOT2 = 24'hB504F3; // Fixed-point representation of sqrt(2) * 2^23

    always @* begin
        if (is_nan) begin
            result = 32'h7FC00000;
        end else if (is_pos_inf) begin
            result = 32'h7F800000;
        end else if (is_neg_inf) begin
            result = 32'h7FC00000;
        end else if (is_zero) begin
            result = 32'h00000000;
        end else if (sign == 1) begin
            // Sqrt(negative) = NaN
            result = 32'h7FC00000;
        end else begin    
            sqrt_exponent <= ((exponent - 8'd127) >> 1) + 8'd127;
            adjusted_mantissa <= {1'b1, mantissa};
            sqrt_mantissa = fixed_sqrt_result;
            if (exponent[0] == 0) begin
                // Odd Exponent Case (as bias is odd)
                product = (sqrt_mantissa * ROOT2);
                sqrt_mantissa = product[46:23] + 1'b1;
            end
            result = {1'b0, sqrt_exponent, sqrt_mantissa[22:0]};
        end
    end
endmodule

EE3403_Project/SquareRoot_tb.v
`timescale 1ns / 1ps

module SquareRoot_tb;
    reg [31:0] floating_point_in;
    reg clk;
    wire [31:0] result;

    // Instantiate the square root module
    SquareRoot uut (
        .floating_point_in(floating_point_in),
        .clk(clk),
        .result(result)
    );

    // Clock
    initial begin
        clk = 0;
        forever #5 clk = ~clk; 
    end

    // Test cases
    initial 
    begin    
        $dumpfile("Squareroot.vcd");
        $dumpvars();

        $display("Time\tclk\tInput\tOutput");
        
        floating_point_in = 32'h41100000; // 9.0
        #10 $display("%0t\t%b\t%h\t%h\n", $time, clk, floating_point_in, result);

        floating_point_in = 32'h40490fda; // 3.141592
        #10 $display("%0t\t%b\t%h\t%h\n", $time, clk, floating_point_in, result);

        floating_point_in = 32'h00000000; // 0.0
        #10 $display("%0t\t%b\t%h\t%h\n", $time, clk, floating_point_in, result);

        floating_point_in = 32'h7F800000; // +INF
        #10 $display("%0t\t%b\t%h\t%h\n", $time, clk, floating_point_in, result);

        floating_point_in = 32'hC0800000; // -4.0
        #10 $display("%0t\t%b\t%h\t%h\n", $time, clk, floating_point_in, result);

        floating_point_in = 32'h40400000; // 3.0
        #10 $display("%0t\t%b\t%h\t%h\n", $time, clk, floating_point_in, result);

        floating_point_in = 32'h41800000; // 16.0
        #10 $display("%0t\t%b\t%h\t%h\n", $time, clk, floating_point_in, result);

        floating_point_in = 32'h5d94c9c2; // pi^pi^pi = 1.3401642e+18
        #10 $display("%0t\t%b\t%h\t%h\n", $time, clk, floating_point_in, result);

        floating_point_in = 32'hFF800000; // -INF
        #10 $display("%0t\t%b\t%h\t%h\n", $time, clk, floating_point_in, result);

        $finish;
    end
endmodule

EE3403_Project/Squareroot.vcd
$date
	Thu Dec 05 20:56:33 2024
$end
$version
	Icarus Verilog
$end
$timescale
	1ps
$end
$scope module SquareRoot_tb $end
$var wire 32 ! result [31:0] $end
$var reg 1 " clk $end
$var reg 32 # floating_point_in [31:0] $end
$scope module uut $end
$var wire 1 " clk $end
$var wire 32 $ floating_point_in [31:0] $end
$var wire 1 % is_nan $end
$var wire 1 & is_neg_inf $end
$var wire 1 ' is_pos_inf $end
$var wire 1 ( is_zero $end
$var wire 1 ) sign $end
$var wire 23 * mantissa [22:0] $end
$var wire 24 + fixed_sqrt_result [23:0] $end
$var wire 8 , exponent [7:0] $end
$var parameter 24 - ROOT2 $end
$var reg 24 . adjusted_mantissa [23:0] $end
$var reg 1 / odd_flag $end
$var reg 47 0 product [46:0] $end
$var reg 32 1 result [31:0] $end
$var reg 8 2 sqrt_exponent [7:0] $end
$var reg 24 3 sqrt_mantissa [23:0] $end
$scope module sqrt_inst $end
$var wire 23 4 Y [22:0] $end
$var wire 1 " clk $end
$var wire 24 5 term1 [23:0] $end
$var wire 24 6 term5 [23:0] $end
$var wire 24 7 term4 [23:0] $end
$var wire 24 8 term3 [23:0] $end
$var wire 24 9 term2 [23:0] $end
$var wire 24 : result [23:0] $end
$var wire 32 ; product [31:0] $end
$var wire 51 < prod [50:0] $end
$var wire 24 = Y_new [23:0] $end
$var wire 6 > Y_cap [5:0] $end
$var wire 24 ? B [23:0] $end
$var wire 24 @ A_raw [23:0] $end
$var wire 7 A A3 [6:0] $end
$var wire 24 B A2_square [23:0] $end
$var wire 24 C A2_cube [23:0] $end
$var wire 24 D A2_A3_prod [23:0] $end
$var wire 7 E A2 [6:0] $end
$var wire 24 F A [23:0] $end
$var reg 28 G M [27:0] $end
$var reg 9 H R [8:0] $end
$upscope $end
$upscope $end
$upscope $end
$enddefinitions $end
$comment Show the parameter values. $end
$dumpall
b101101010000010011110011 -
$end
#0
$dumpvars
bx H
bx G
bx F
bx E
b0xxxxxxxxxxxx D
b0xxxxx C
b0xxxxxxxxxxxxxxxxxxx B
bx A
bx @
bx ?
b1000 >
b100100000000000000000000 =
bx <
bx ;
bx :
b0xxxxxxxxxxxxxxxxxxxxxxx 9
b0xxxxxxxxxxxxxxxx 8
b0xxxxxxxxxx 7
b0x 6
b100000000000000000000000 5
b100000000000000000000 4
bx 3
b10000000 2
b10000000xxxxxxxxxxxxxxxxxxxxxxx 1
bx 0
0/
b100100000000000000000000 .
b10000010 ,
bx +
b100000000000000000000 *
0)
0(
0'
0&
0%
b1000001000100000000000000000000 $
b1000001000100000000000000000000 #
0"
b10000000xxxxxxxxxxxxxxxxxxxxxxx !
$end
#5000
b1000000010000000000000000000000 !
b1000000010000000000000000000000 1
b10111111111111111111111100110111001110111000010 0
b110000000000000000000000 3
b100001111100001110110110 +
b100001111100001110110110 :
b100001111100001110110110100111111000001001100110110 <
b11111111101011111111010 ?
b110 8
b0 6
b0 7
b110010 B
b0 C
b0 D
b10100000000000 9
b101000 E
b0 A
b101000000000000 F
b111111111011000000000000 @
b1000011111101110001101110111 G
b1111111101100000000000000000000 ;
b11100011 H
1"
#10000
b101 8
b110010010010010000111 9
b11100101111111101010110100001000101101101011001 0
b101000 B
b101000101010000110000011 +
b101000101010000110000011 :
b100100 E
b1000011 A
b101000101010000110000011010100010110011111001101110 <
b100110010010010010000010 ?
b1100100100100100001110 F
b1100100100100100001110 @
b100100 >
b10110010010010010000111001001110 ;
b110010010000111111011010 =
b10010010000111111011010 4
b111111111001011111111010101110 !
b111111111001011111111010101110 1
b110010010000111111011010 .
b1111111 2
b111001011111111010101110 3
b10000000 ,
b10010010000111111011010 *
0"
b1000000010010010000111111011010 #
b1000000010010010000111111011010 $
#15000
b100000000000001010001011 ?
b0 8
b1010001011 9
b0 B
b10 E
b1000101 A
b111111111000101101111111000010 !
b111111111000101101111111000010 1
b11100010110111111100000101111000110111101010101 0
b111000101101111111000010 3
b10100010111 F
b101000000110110010010111 +
b101000000110110010010111 :
b10100010111 @
b101000000110110010010111100110000001010110101010100 <
b1010000001101001011001111100 G
b10000000000001010001011111001110 ;
b10100011 H
1"
#20000
b10000 8
b101110100000000000000 9
b10000000 B
b100000110100011000101110 +
b100000110100011000101110 :
b1000000 E
b0 A
b100000110100011000101110010110100111001100001000000 <
b11010001011111111110000 ?
b1011101000000000000000 F
b110100011000000000000000 @
b0 >
b1010001100000000000000000000000 ;
b100000000000000000000000 =
b0 4
b100000000000000000000000 .
b10111111 2
b0 !
b0 1
1(
b111000101101111111000010 3
b0 ,
b0 *
0"
b0 #
b0 $
#25000
b0 8
b0 9
b0 B
b0 E
b100000000000000000000000 ?
b0 F
b100000000000000000000000 +
b100000000000000000000000 :
b0 @
b100000000000000000000000000000000000000000000000000 <
b1000000000000000000000000000 G
b10000000000000000000000000000000 ;
b100000000 H
1"
#30000
1'
b1111111100000000000000000000000 !
b1111111100000000000000000000000 1
b100000000000000000000000 3
0(
b11111111 ,
0"
b1111111100000000000000000000000 #
b1111111100000000000000000000000 $
#35000
1"
#40000
b1111111110000000000000000000000 !
b1111111110000000000000000000000 1
0'
1)
b10000001 ,
0"
b11000000100000000000000000000000 #
b11000000100000000000000000000000 $
#45000
1"
#50000
b101000000000000000000000 +
b101000000000000000000000 :
b101000000000000000000000000000000000000000000000000 <
b101000000000000000000000 ?
b1000000000000000000000 9
b10000000000000000000000 F
b10000000000000000000000 @
b100000 >
b11000000000000000000000000000000 ;
b110000000000000000000000 =
b10000000000000000000000 4
b110000000000000000000000 .
b1111111 2
b111111111000100100011000110000 !
b111111111000100100011000110000 1
b111000100100011000110000 3
b11100010010001100010111111000000000000000000000 0
0)
b10000000 ,
b10000000000000000000000 *
0"
b1000000010000000000000000000000 #
b1000000010000000000000000000000 $
#55000
b10000 8
b100000000000000 9
b10000000 B
b1000000 E
b11111111011111111110000 ?
b111111110111011011001111010111 !
b111111110111011011001111010111 1
b11011101101100111101011000100000011011001010000 0
b110111011011001111010111 3
b1000000000000000 F
b100111001100010001110000 +
b100111001100010001110000 :
b111111111000000000000000 @
b100111001100010001110000101001101011011001000110000 <
b1001110100010011000011011101 G
b1111111100000000000000000000000 ;
b10101010 H
1"
#60000
b100000101011000011011010 +
b100000101011000011011010 :
b100000101011000011011010011111100001000000000000000 <
b11010101000000000000000 ?
b0 8
b101011000000000000000 9
b0 B
b0 E
b1010110000000000000000 F
b110101010000000000000000 @
b0 >
b1010101000000000000000000000000 ;
b100000000000000000000000 =
b0 4
b100000000000000000000000 .
b10000001 2
b1000000100000101011000011011010 !
b1000000100000101011000011011010 1
b100000101011000011011010 3
b10000011 ,
b0 *
0"
b1000001100000000000000000000000 #
b1000001100000000000000000000000 $
#65000
b0 9
b100000000000000000000000 ?
b0 F
b1000000100000000000000000000000 !
b1000000100000000000000000000000 1
b100000000000000000000000 3
b100000000000000000000000 +
b100000000000000000000000 :
b0 @
b100000000000000000000000000000000000000000000000000 <
b1000000000000000000000000000 G
b10000000000000000000000000000000 ;
b100000000 H
1"
#70000
b100010100110010010111010 3
b100010100110010010111010 +
b100010100110010010111010 :
b100010100110010010111010000000000000000000000000000 <
b100010100110010010111010 ?
b100111 8
b10100110010011100001 9
b100111000 B
b1 C
b10 D
b1100100 E
b1110000 A
b101001100100111000010 F
b101001100100111000010 @
b1010 >
b10010100110010011100001000000000 ;
b100101001100100111000010 =
b101001100100111000010 4
b1001110100010100110010010111010 !
b1001110100010100110010010111010 1
b100101001100100111000010 .
b10011101 2
b10111011 ,
b101001100100111000010 *
0"
b1011101100101001100100111000010 #
b1011101100101001100100111000010 $
#75000
b100000000011100100001010 ?
b1100 8
b11100100010110 9
b1100101 B
b0 C
b0 D
b111001 E
b1011 A
b1001110100010100000000011010001 !
b1001110100010100000000011010001 1
b100010100000000011010001 3
b111001000101100 F
b100010100000000011010001 +
b100010100000000011010001 :
b111001000101100 @
b100010100000000011010001001010011111100101001011100 <
b1000100111000011011011010110 G
b10000000011100100010110001111010 ;
b11011101 H
1"
#80000
1&
0'
b1111111110000000000000000000000 !
b1111111110000000000000000000000 1
1)
b11111111 ,
b0 *
0"
b11111111100000000000000000000000 #
b11111111100000000000000000000000 $
